spire/__init__.py
spire/doc/AutoFitBehaviorType.py
spire/doc/Background.py
spire/doc/BackgroundGradient.py
spire/doc/Body.py
spire/doc/BodyRegion.py
spire/doc/Bookmark.py
spire/doc/BookmarkEnd.py
spire/doc/BookmarkStart.py
spire/doc/BookmarkTextStyle.py
spire/doc/Break.py
spire/doc/BuiltinDocumentProperties.py
spire/doc/CaptionNumberingFormat.py
spire/doc/CaptionPosition.py
spire/doc/CellWidthType.py
spire/doc/CharacterSpacing.py
spire/doc/Column.py
spire/doc/CssStyleSheetType.py
spire/doc/CustomDocumentProperties.py
spire/doc/DifferRevisions.py
spire/doc/Document.py
spire/doc/DocumentBase.py
spire/doc/DocumentContainer.py
spire/doc/DocumentObject.py
spire/doc/DocumentProperties.py
spire/doc/DocumentProperty.py
spire/doc/DocumentSecurity.py
spire/doc/DocumentViewType.py
spire/doc/Endnote.py
spire/doc/EndnotePosition.py
spire/doc/FieldType.py
spire/doc/FileFormat.py
spire/doc/FootEndnoteOptions.py
spire/doc/FootnoteBody.py
spire/doc/FootnoteNumberFormat.py
spire/doc/FootnotePosition.py
spire/doc/FootnoteRestartRule.py
spire/doc/FootnoteType.py
spire/doc/FrameSizeRule.py
spire/doc/HeaderFooter.py
spire/doc/HeaderType.py
spire/doc/HeadersFooters.py
spire/doc/HorizontalPosition.py
spire/doc/HorizontalRelation.py
spire/doc/HtmlExportListLabelsType.py
spire/doc/HtmlExportOptions.py
spire/doc/HttpContentType.py
spire/doc/Hyperlink.py
spire/doc/Hyphenation.py
spire/doc/LayoutType.py
spire/doc/LineDashing.py
spire/doc/LineNumberingRestartMode.py
spire/doc/LineSpacingRule.py
spire/doc/LocaleIDs.py
spire/doc/MailMergeMainDocumentType.py
spire/doc/MarkdownExportOptions.py
spire/doc/MarkdownLinkOutputMode.py
spire/doc/MarkdownListOutputMode.py
spire/doc/MarkdownOfficeMathOutputMode.py
spire/doc/MarkdownSaveAsHtml.py
spire/doc/OdsoRecipientData.py
spire/doc/OdsoRecipientDataCollection.py
spire/doc/OutlineLevel.py
spire/doc/OwnerHolder.py
spire/doc/PageBorderOffsetFrom.py
spire/doc/PageBordersApplyType.py
spire/doc/PageSetup.py
spire/doc/PdfConformanceLevel.py
spire_doc-14.1.0.dist-info/METADATA
spire_doc-14.1.0.dist-info/WHEEL
spire_doc-14.1.0.dist-info/top_level.txt
spire_doc-14.1.0.dist-info/RECORD
